[
 /* these are parts of the foreign key to tuple */
 {
     "attr_index": 0,
     "attr_name": "ns_name",
     "attr_type": "string",
     "attr_required": true,
 },
 {
     "attr_index": 1,
     "attr_name": "type_name",
     "attr_type": "string",
     "attr_required": true,
 },
 /* unique things about a key: its name */
 {
     "attr_index": 2,
     "attr_name": "key_name",
     "attr_type": "string",
     "attr_required": true
 },
 /* does this apply to sub-types? */
 {
     "attr_index": 3,
     "attr_name": "key_inherit",
     "attr_type": "bool",
     "attr_required": true
 },
 /* an ordered list of attributes */
 {
     "attr_index": 4,
     "attr_name": "key_attr_index",
     "attr_type": "int",
     "attr_required": true,
     "attr_dim": 1
 },
]
